LICENSE
README.md
setup.py
prometheus_runtime_exporter/__init__.py
prometheus_runtime_exporter/exporter.py
prometheus_runtime_exporter/runtime.py
prometheus_runtime_exporter.egg-info/PKG-INFO
prometheus_runtime_exporter.egg-info/SOURCES.txt
prometheus_runtime_exporter.egg-info/dependency_links.txt
prometheus_runtime_exporter.egg-info/requires.txt
prometheus_runtime_exporter.egg-info/top_level.txt