Metadata-Version: 2.1
Name: prometheus-runtime-exporter
Version: 1.0
Summary: Python Runtime metrics prometheus exporter
Home-page: https://github.com/dream-mo/prometheus-runtime-exporter
Author: dreammo
Author-email: dreammovip@163.com
License: Apache License
Keywords: prometheus exporter runtime
Platform: UNKNOWN
License-File: LICENSE
